{
  "init_bboxes": {
    "1": {
      "0": [
        null,
        [756.01, 374.75, 849.88, 604.43],
        [1134.37, 357.18, 1271.42, 638.76],
        [994.67, 385.74, 1168.40, 798.33]
      ],
      "1": [
        null,
        [756, 375, 850, 603],
        [1138, 356, 1272, 637],
        [995, 385, 1168, 797]
      ],
      "2": [
        null,
        [756, 375, 851, 603],
        [1132, 355, 1273, 639],
        [992, 385, 1169, 797]
      ],
      "3": [
        null,
        [755, 376, 851, 603],
        [1130, 358, 1273, 640],
        [995, 389, 1170, 800]
      ],
      "4": [
        null,
        [754, 377, 852, 603],
        [1134, 359, 1275, 642],
        [993, 391, 1170, 801]
      ],
      "5": [
        null,
        [754, 377, 854, 603],
        [1129, 361, 1276, 644],
        [991, 393, 1171, 801]
      ],
      "6": [
        null,
        [753, 378, 851, 604],
        [1134, 361, 1276, 642],
        [990, 393, 1170, 803]
      ],
      "7": [
        null,
        [753, 379, 853, 604],
        [1134, 361, 1277, 643],
        [990, 392, 1170, 802]
      ],
      "8": [
        null,
        [753, 379, 855, 604],
        [1133, 362, 1277, 643],
        [991, 392, 1170, 802]
      ],
      "9": [
        null,
        [754, 379, 855, 604],
        [1131, 362, 1277, 644],
        [990, 391, 1170, 802]
      ],
      "10": [
        null,
        [753, 379, 859, 604],
        [1129, 362, 1276, 644],
        [988, 392, 1171, 799]
      ],
      "11": [
        null,
        [754, 379, 862, 603],
        [1126, 363, 1276, 644],
        [982, 392, 1170, 798]
      ],
      "12": [
        null,
        [755, 379, 866, 603],
        [1124, 363, 1275, 643],
        [975, 391, 1170, 800]
      ],
      "13": [
        null,
        [755, 380, 870, 603],
        [1120, 364, 1274, 644],
        [969, 392, 1170, 800]
      ],
      "14": [
        null,
        [757, 380, 873, 603],
        [1113, 364, 1274, 645],
        [965, 394, 1170, 801]
      ],
      "15": [
        null,
        [757, 380, 873, 603],
        [1107, 364, 1274, 645],
        [960, 393, 1170, 801]
      ],
      "16": [
        null,
        [757, 380, 873, 603],
        [1102, 364, 1274, 645],
        [959, 394, 1170, 801]
      ],
      "17": [
        null,
        [758, 381, 873, 603],
        [1100, 364, 1274, 646],
        [958, 395, 1170, 801]
      ],
      "18": [
        null,
        [759, 381, 873, 603],
        [1100, 364, 1275, 646],
        [958, 395, 1170, 801]
      ],
      "19": [
        null,
        [759, 381, 873, 603],
        [1099, 364, 1275, 646],
        [957, 396, 1171, 801]
      ],
      "20": [
        null,
        [760, 381, 873, 603],
        [1100, 364, 1274, 646],
        [956, 394, 1170, 801]
      ],
      "21": [
        null,
        [760, 381, 873, 603],
        [1100, 365, 1274, 647],
        [957, 394, 1170, 801]
      ],
      "22": [
        null,
        [761, 380, 873, 602],
        [1100, 366, 1274, 646],
        [957, 395, 1169, 801]
      ],
      "23": [
        null,
        [762, 380, 873, 603],
        [1098, 367, 1274, 646],
        [957, 397, 1170, 801]
      ],
      "24": [
        null,
        [762, 381, 874, 603],
        [1100, 366, 1273, 646],
        [957, 396, 1169, 801]
      ],
      "25": [
        null,
        [763, 381, 873, 603],
        [1100, 367, 1273, 645],
        [956, 395, 1169, 802]
      ],
      "26": [
        null,
        [763, 380, 874, 603],
        [1101, 367, 1273, 646],
        [953, 395, 1170, 802]
      ],
      "27": [
        null,
        [763, 380, 875, 604],
        [1096, 367, 1273, 645],
        [956, 395, 1171, 801]
      ],
      "28": [
        null,
        [763, 379, 875, 604],
        [1096, 366, 1274, 646],
        [943, 382, 1173, 803]
      ],
      "29": [
        null,
        [763, 378, 876, 604],
        [1093, 365, 1274, 645],
        [953, 393, 1173, 806]
      ],
      "30": [
        null,
        [764, 378, 875, 604],
        [1092, 364, 1274, 645],
        [956, 392, 1174, 808]
      ],
      "31": [
        null,
        [764, 378, 874, 603],
        [1090, 365, 1274, 647],
        [956, 390, 1171, 809]
      ],
      "32": [
        null,
        [766, 377, 875, 603],
        [1090, 365, 1276, 648],
        [956, 389, 1164, 812]
      ],
      "33": [
        null,
        [765, 376, 875, 603],
        [1092, 364, 1276, 649],
        [957, 388, 1159, 812]
      ],
      "34": [
        null,
        [764, 376, 874, 603],
        [1090, 365, 1277, 652],
        [957, 388, 1153, 814]
      ],
      "35": [
        null,
        [764, 376, 878, 603],
        [1091, 365, 1279, 652],
        [956, 387, 1146, 817]
      ],
      "36": [
        null,
        [765, 374, 875, 603],
        [1094, 364, 1280, 653],
        [954, 385, 1141, 751]
      ],
      "37": [
        null,
        [762, 374, 875, 604],
        [1099, 364, 1280, 655],
        [956, 388, 1137, 822]
      ],
      "38": [
        null,
        [762, 375, 874, 604],
        [1100, 364, 1282, 659],
        [956, 387, 1136, 823]
      ],
      "39": [
        null,
        [762, 375, 875, 604],
        [1100, 365, 1283, 663],
        [953, 389, 1135, 829]
      ]
    },
    "2": {
      "0": [
        [963.80, 362.06, 1057.09, 625.97],
        [929.63, 376.49, 1040.63, 604.58],
        [896.62, 361.01, 1057.46, 636.03],
        [768.83, 370.84, 944.67, 702.90]
      ],
      "1": [
        [963, 362, 1057, 628],
        [929, 376, 1040, 604],
        [896, 360, 1057, 636],
        [768, 364, 944, 702]
      ],
      "2": [
        [961, 362, 1057, 625],
        [928, 377, 1040, 604],
        [897, 360, 1057, 636],
        [769, 360, 945, 702]
      ],
      "3": [
        [960, 362, 1058, 625],
        [924, 375, 1040, 604],
        [899, 359, 1057, 635],
        [768, 361, 945, 702]
      ],
      "4": [
        [961, 359, 1058, 608],
        [922, 377, 1040, 604],
        [901, 360, 1057, 635],
        [771, 396, 945, 702]
      ],
      "5": [
        [957, 360, 1057, 603],
        [920, 376, 1040, 604],
        [901, 360, 1058, 635],
        [774, 368, 945, 702]
      ],
      "6": [
        [956, 360, 1058, 593],
        [917, 376, 1040, 605],
        [902, 360, 1057, 635],
        [774, 356, 945, 702]
      ],
      "7": [
        [950, 360, 1050, 592],
        [928, 374, 1040, 605],
        [900, 360, 1059, 635],
        [775, 361, 946, 702]
      ],
      "8": [
        [950, 359, 1047, 600],
        [919, 375, 1040, 605],
        [902, 360, 1059, 635],
        [777, 360, 946, 702]
      ],
      "9": [
        [949, 358, 1047, 589],
        [921, 373, 1040, 606],
        [899, 359, 1058, 636],
        [777, 364, 955, 703]
      ],
      "10": [
        [951, 358, 1046, 591],
        [919, 373, 1040, 604],
        [898, 358, 1058, 636],
        [784, 373, 960, 702]
      ],
      "11": [
        [949, 356, 1038, 589],
        [921, 372, 1040, 603],
        [899, 358, 1058, 636],
        [785, 356, 963, 703]
      ],
      "12": [
        [949, 356, 1036, 590],
        [921, 373, 1038, 603],
        [900, 357, 1058, 636],
        [790, 361, 965, 704]
      ],
      "13": [
        [949, 356, 1035, 589],
        [918, 373, 1036, 604],
        [901, 358, 1058, 636],
        [796, 356, 966, 704]
      ],
      "14": [
        [948, 356, 1035, 586],
        [920, 372, 1034, 605],
        [901, 357, 1058, 636],
        [800, 357, 967, 704]
      ],
      "15": [
        [950, 352, 1033, 584],
        [918, 372, 1033, 609],
        [905, 358, 1057, 636],
        [804, 356, 968, 704]
      ],
      "16": [
        [949, 352, 1034, 585],
        [925, 371, 1032, 612],
        [907, 357, 1057, 636],
        [810, 356, 967, 704]
      ],
      "17": [
        [947, 352, 1034, 584],
        [923, 372, 1029, 613],
        [910, 357, 1057, 636],
        [814, 357, 968, 704]
      ],
      "18": [
        [947, 352, 1034, 584],
        [920, 372, 1025, 615],
        [924, 357, 1057, 636],
        [819, 354, 965, 704]
      ],
      "19": [
        [949, 353, 1034, 586],
        [917, 372, 1023, 618],
        [925, 357, 1057, 636],
        [829, 355, 962, 704]
      ],
      "20": [
        [950, 352, 1035, 590],
        [916, 372, 1022, 619],
        [930, 356, 1058, 636],
        [834, 354, 962, 704]
      ],
      "21": [
        [950, 354, 1035, 590],
        [913, 371, 1018, 620],
        [930, 355, 1058, 636],
        [839, 353, 956, 704]
      ],
      "22": [
        [949, 357, 1037, 589],
        [911, 372, 1017, 622],
        [940, 356, 1058, 636],
        [847, 353, 963, 704]
      ],
      "23": [
        [947, 354, 1038, 590],
        [908, 372, 1017, 623],
        [944, 355, 1056, 635],
        [849, 354, 959, 704]
      ],
      "24": [
        [945, 353, 1038, 590],
        [909, 372, 1018, 623],
        [946, 355, 1055, 635],
        [849, 354, 960, 705]
      ],
      "25": [
        [944, 352, 1039, 588],
        [908, 373, 1018, 623],
        [947, 355, 1056, 635],
        [848, 354, 966, 704]
      ],
      "26": [
        [943, 348, 1039, 588],
        [907, 374, 1018, 623],
        [946, 356, 1055, 635],
        [843, 357, 987, 705]
      ],
      "27": [
        [940, 352, 1041, 588],
        [911, 375, 1018, 623],
        [946, 357, 1056, 635],
        [840, 355, 953, 704]
      ],
      "28": [
        [940, 351, 1041, 589],
        [909, 373, 1019, 624],
        [945, 357, 1055, 636],
        [840, 355, 952, 705]
      ],
      "29": [
        [940, 352, 1042, 589],
        [904, 375, 1018, 624],
        [946, 358, 1055, 635],
        [839, 394, 951, 702]
      ],
      "30": [
        [940, 352, 1043, 589],
        [910, 375, 1018, 623],
        [947, 357, 1055, 636],
        [841, 385, 947, 700]
      ],
      "31": [
        [937, 355, 1046, 589],
        [908, 374, 1017, 623],
        [947, 357, 1054, 633],
        [840, 357, 950, 702]
      ],
      "32": [
        [937, 358, 1048, 589],
        [907, 374, 1018, 623],
        [946, 357, 1058, 635],
        [839, 358, 957, 703]
      ],
      "33": [
        [937, 358, 1048, 589],
        [904, 374, 1017, 622],
        [945, 358, 1057, 632],
        [839, 382, 953, 702]
      ],
      "34": [
        [938, 357, 1047, 589],
        [893, 373, 1017, 622],
        [945, 359, 1062, 633],
        [841, 388, 961, 704]
      ],
      "35": [
        [937, 346, 1048, 588],
        [891, 372, 1017, 621],
        [945, 355, 1065, 633],
        [842, 385, 954, 707]
      ],
      "36": [
        [938, 344, 1048, 588],
        [889, 372, 1017, 622],
        [945, 355, 1070, 635],
        [842, 371, 957, 711]
      ],
      "37": [
        [938, 343, 1038, 588],
        [887, 405, 1018, 621],
        [946, 354, 1071, 636],
        [844, 358, 973, 715]
      ],
      "38": [
        [940, 342, 1027, 589],
        [887, 385, 1018, 621],
        [946, 354, 1078, 637],
        [846, 365, 975, 717]
      ],
      "39": [
        [941, 344, 1035, 589],
        [887, 374, 1018, 622],
        [945, 353, 1083, 637],
        [847, 358, 976, 719]
      ]
    }
  }
}
