{
  "init_bboxes": {
    "1": {
      "0": [
        [1022.30, 366.57, 1138.33, 541.65],
        [764.72, 393.50, 835.73, 592.48],
        [1161.86, 408.94, 1258.86, 731.91],
        [874.62, 459.69, 1044.91, 915.14]
      ],
      "1": [
        [1025, 367, 1140, 542],
        [762, 405, 823, 591],
        [1162, 413, 1267, 737],
        [877, 466, 1028, 924]
      ],
      "2": [
        [1029, 367, 1145, 541],
        [759, 417, 818, 591],
        [1161, 414, 1278, 740],
        [874, 474, 1052, 928]
      ],
      "3": [
        [1028, 370, 1147, 539],
        [757, 403, 821, 590],
        [1162, 417, 1283, 740],
        [875, 481, 1053, 940]
      ],
      "4": [
        [1026, 378, 1147, 540],
        [755, 405, 818, 590],
        [1164, 422, 1295, 739],
        [873, 485, 1054, 960]
      ],
      "5": [
        [1026, 386, 1149, 538],
        [751, 408, 834, 591],
        [1163, 423, 1300, 748],
        [875, 490, 1055, 965]
      ],
      "6": [
        [1028, 388, 1148, 539],
        [751, 409, 834, 591],
        [1160, 425, 1308, 755],
        [869, 512, 1053, 967]
      ],
      "7": [
        [1026, 399, 1151, 538],
        null,
        [1165, 440, 1309, 757],
        [871, 522, 1054, 969]
      ],
      "8": [
        [1033, 397, 1151, 537],
        [750, 416, 845, 590],
        [1159, 451, 1313, 757],
        [870, 525, 1063, 968]
      ],
      "9": [
        [1032, 398, 1152, 537],
        [750, 417, 843, 590],
        [1161, 456, 1314, 758],
        [868, 527, 1061, 967]
      ],
      "10": [
        [1032, 398, 1151, 537],
        [750, 419, 844, 589],
        [1164, 459, 1313, 758],
        [869, 529, 1065, 967]
      ],
      "11": [
        [1011, 399, 1147, 571],
        null,
        [1164, 461, 1313, 758],
        [869, 529, 1070, 967]
      ],
      "12": [
        [1008, 392, 1150, 575],
        null,
        [1167, 461, 1313, 758],
        [868, 527, 1070, 967]
      ],
      "13": [
        null,
        null,
        [1169, 460, 1313, 758],
        [867, 527, 1075, 967]
      ],
      "14": [
        [1011, 394, 1150, 545],
        null,
        [1167, 458, 1314, 758],
        [866, 507, 1075, 966]
      ],
      "15": [
        [1009, 395, 1149, 572],
        null,
        [1157, 459, 1312, 757],
        [867, 505, 1070, 965]
      ],
      "16": [
        [1008, 402, 1149, 575],
        null,
        [1144, 459, 1312, 757],
        [871, 516, 1064, 960]
      ],
      "17": [
        [1007, 396, 1148, 575],
        null,
        [1142, 458, 1311, 758],
        [873, 519, 1059, 955]
      ],
      "18": [
        [1007, 397, 1148, 576],
        null,
        [1138, 446, 1309, 756],
        [876, 517, 1057, 949]
      ],
      "19": [
        [1008, 397, 1146, 575],
        null,
        [1117, 427, 1303, 753],
        [878, 511, 1052, 930]
      ],
      "20": [
        [971, 399, 1146, 576],
        null,
        [1119, 427, 1305, 752],
        [876, 511, 1048, 927]
      ],
      "21": [
        [1006, 397, 1146, 576],
        null,
        [1125, 440, 1302, 743],
        [873, 510, 1054, 926]
      ],
      "22": [
        [973, 397, 1144, 576],
        null,
        [1144, 425, 1296, 739],
        [867, 507, 1055, 928]
      ],
      "23": [
        [974, 395, 1141, 576],
        null,
        [1159, 431, 1288, 737],
        [873, 502, 1055, 919]
      ],
      "24": [
        [974, 399, 1139, 576],
        null,
        [1161, 430, 1287, 736],
        [873, 499, 1054, 909]
      ],
      "25": [
        [976, 395, 1137, 578],
        null,
        null,
        [872, 494, 1056, 896]
      ],
      "26": [
        [976, 395, 1136, 578],
        null,
        null,
        [868, 490, 1057, 889]
      ],
      "27": [
        null,
        null,
        null,
        [880, 486, 1057, 841]
      ],
      "28": [
        [1024, 391, 1135, 547],
        null,
        null,
        [879, 485, 1057, 838]
      ],
      "29": [
        [1002, 396, 1129, 573],
        null,
        null,
        [876, 482, 1057, 836]
      ],
      "30": [
        [976, 400, 1130, 576],
        null,
        null,
        [870, 478, 1058, 837]
      ],
      "31": [
        null,
        null,
        null,
        [862, 477, 1058, 838]
      ],
      "32": [
        null,
        null,
        null,
        [841, 477, 1059, 838]
      ],
      "33": [
        null,
        null,
        null,
        [837, 476, 1059, 837]
      ],
      "34": [
        null,
        null,
        null,
        [838, 476, 1061, 837]
      ],
      "35": [
        [1010, 388, 1120, 568],
        null,
        null,
        [836, 474, 1062, 832]
      ],
      "36": [
        [1004, 385, 1120, 569],
        null,
        null,
        [835, 474, 1062, 828]
      ],
      "37": [
        [1004, 386, 1120, 570],
        null,
        null,
        [835, 472, 1061, 827]
      ],
      "38": [
        [1006, 380, 1120, 569],
        null,
        null,
        [835, 473, 1061, 826]
      ],
      "39": [
        [1007, 382, 1120, 567],
        null,
        null,
        [835, 474, 1060, 823]
      ]
    },
    "2": {
      "0": [
        [938.69, 367.75, 1042.33, 576.98],
        [820.89, 400.88, 915.70, 613.45],
        [1047.39, 387.11, 1157.98, 653.67],
        null
      ],
      "1": [
        [943, 368, 1045, 577],
        [819, 397, 915, 613],
        [1046, 386, 1159, 656],
        null
      ],
      "2": [
        [943, 368, 1044, 577],
        [819, 398, 915, 609],
        [1046, 385, 1164, 659],
        null
      ],
      "3": [
        [944, 369, 1044, 578],
        [815, 398, 916, 611],
        [1045, 383, 1162, 660],
        null
      ],
      "4": [
        [949, 371, 1046, 578],
        [810, 397, 916, 613],
        [1045, 390, 1165, 659],
        null
      ],
      "5": [
        [953, 372, 1046, 578],
        [812, 394, 916, 612],
        [1045, 389, 1168, 659],
        null
      ],
      "6": [
        [956, 375, 1055, 577],
        [806, 394, 915, 612],
        [1045, 390, 1171, 659],
        null
      ],
      "7": [
        [959, 374, 1082, 577],
        [801, 390, 916, 602],
        [1045, 393, 1174, 659],
        null
      ],
      "8": [
        [963, 375, 1053, 576],
        [797, 404, 915, 604],
        [1045, 392, 1175, 659],
        null
      ],
      "9": [
        [967, 375, 1048, 575],
        [796, 396, 915, 605],
        [1045, 391, 1177, 659],
        null
      ],
      "10": [
        [968, 379, 1050, 567],
        [790, 399, 912, 602],
        [1045, 398, 1180, 659],
        null
      ],
      "11": [
        [970, 384, 1049, 563],
        [786, 400, 911, 601],
        [1046, 400, 1190, 659],
        null
      ],
      "12": [
        [971, 385, 1051, 558],
        [783, 401, 910, 600],
        [1046, 401, 1195, 660],
        null
      ],
      "13": [
        [970, 390, 1060, 569],
        [778, 404, 909, 599],
        [1048, 405, 1193, 663],
        null
      ],
      "14": [
        [971, 394, 1058, 556],
        [774, 415, 909, 599],
        [1051, 412, 1192, 660],
        null
      ],
      "15": [
        [969, 403, 1053, 545],
        [774, 417, 909, 598],
        [1053, 415, 1210, 664],
        null
      ],
      "16": [
        [970, 402, 1059, 549],
        [774, 412, 910, 599],
        [1052, 418, 1209, 663],
        null
      ],
      "17": [
        [970, 411, 1057, 541],
        [774, 421, 910, 599],
        [1052, 429, 1212, 664],
        null
      ],
      "18": [
        [970, 415, 1055, 541],
        [774, 427, 910, 599],
        [1051, 442, 1215, 667],
        null
      ],
      "19": [
        [971, 417, 1053, 541],
        [776, 442, 911, 600],
        [1051, 453, 1215, 670],
        null
      ],
      "20": [
        [972, 420, 1052, 538],
        [776, 443, 911, 599],
        [1051, 456, 1215, 664],
        null
      ],
      "21": [
        null,
        [775, 442, 912, 599],
        [1050, 463, 1217, 664],
        null
      ],
      "22": [
        null,
        [774, 445, 913, 600],
        [1050, 464, 1196, 660],
        null
      ],
      "23": [
        null,
        [774, 446, 913, 600],
        [1049, 462, 1194, 659],
        null
      ],
      "24": [
        null,
        [774, 444, 913, 600],
        [1049, 472, 1192, 660],
        [878, 523, 954, 736]
      ],
      "25": [
        null,
        [774, 444, 913, 600],
        [1049, 477, 1190, 659],
        [878, 521, 956, 736]
      ],
      "26": [
        null,
        [773, 444, 913, 600],
        null,
        null
      ],
      "27": [
        null,
        [774, 423, 911, 600],
        null,
        null
      ],
      "28": [
        null,
        [773, 432, 913, 600],
        null,
        null
      ],
      "29": [
        null,
        [773, 419, 910, 600],
        null,
        null
      ],
      "30": [
        null,
        [774, 424, 912, 600],
        null,
        null
      ],
      "31": [
        null,
        [773, 421, 910, 600],
        null,
        null
      ],
      "32": [
        null,
        [773, 422, 911, 600],
        null,
        null
      ],
      "33": [
        null,
        [774, 419, 910, 599],
        null,
        null
      ],
      "34": [
        null,
        [772, 416, 910, 599],
        null,
        null
      ],
      "35": [
        null,
        [773, 413, 911, 599],
        null,
        null
      ],
      "36": [
        null,
        [772, 410, 910, 600],
        null,
        null
      ],
      "37": [
        null,
        [772, 411, 910, 600],
        null,
        null
      ],
      "38": [
        null,
        [781, 424, 911, 601],
        null,
        null
      ],
      "39": [
        null,
        [786, 414, 910, 601],
        null,
        null
      ]
    }
  }
}
