{
  "init_bboxes": {
    "1": {
      "0": [
        [866.82, 397.68, 1029.66, 592.14],
        null,
        [965.06, 402.38, 1117.19, 598.36],
        [815.44, 410.29, 1089.04, 671.74]
      ],
      "1": [
        [865, 398, 1022, 592],
        null,
        [965, 407, 1116, 598],
        [821, 409, 1086, 670]
      ],
      "2": [
        [865, 396, 1019, 592],
        null,
        [966, 420, 1117, 598],
        [825, 408, 1073, 667]
      ],
      "3": [
        [865, 394, 991, 590],
        null,
        [964, 399, 1116, 598],
        [839, 407, 1075, 668]
      ],
      "4": [
        [865, 394, 1000, 591],
        null,
        [964, 400, 1116, 599],
        [850, 406, 1073, 668]
      ],
      "5": [
        [865, 393, 996, 591],
        null,
        [963, 396, 1116, 599],
        [861, 405, 1074, 668]
      ],
      "6": [
        [866, 394, 993, 590],
        null,
        [967, 403, 1116, 600],
        [858, 405, 1073, 668]
      ],
      "7": [
        [866, 395, 995, 590],
        null,
        [965, 395, 1115, 598],
        [860, 406, 1073, 668]
      ],
      "8": [
        [866, 395, 995, 590],
        null,
        [968, 397, 1116, 598],
        [861, 406, 1077, 670]
      ],
      "9": [
        [866, 395, 995, 591],
        null,
        [968, 399, 1116, 599],
        [862, 406, 1081, 672]
      ],
      "10": [
        [866, 394, 995, 591],
        null,
        [967, 397, 1116, 598],
        [862, 406, 1083, 674]
      ],
      "11": [
        [866, 392, 991, 591],
        null,
        [969, 397, 1116, 596],
        [862, 405, 1082, 672]
      ],
      "12": [
        [865, 392, 991, 591],
        null,
        [971, 398, 1116, 596],
        [861, 405, 1079, 670]
      ],
      "13": [
        [865, 391, 988, 591],
        null,
        [972, 409, 1116, 596],
        [862, 404, 1082, 672]
      ],
      "14": [
        [865, 389, 995, 591],
        null,
        [973, 408, 1114, 595],
        [862, 406, 1082, 671]
      ],
      "15": [
        [865, 389, 991, 592],
        [962, 417, 1015, 573],
        [974, 399, 1113, 594],
        [862, 405, 1081, 672]
      ],
      "16": [
        [864, 387, 990, 591],
        [959, 417, 1014, 573],
        [974, 411, 1113, 595],
        [863, 405, 1076, 670]
      ],
      "17": [
        [864, 388, 986, 592],
        [957, 421, 1013, 573],
        [976, 395, 1112, 596],
        [862, 404, 1070, 667]
      ],
      "18": [
        [864, 386, 980, 592],
        [956, 420, 1015, 574],
        [978, 390, 1108, 587],
        [864, 404, 1073, 667]
      ],
      "19": [
        [864, 384, 978, 592],
        [958, 421, 1015, 575],
        [981, 389, 1106, 586],
        [864, 401, 1074, 667]
      ],
      "20": [
        [864, 385, 978, 593],
        [957, 421, 1015, 575],
        [980, 389, 1097, 582],
        [863, 402, 1078, 669]
      ],
      "21": [
        [865, 384, 977, 593],
        [957, 422, 1015, 575],
        [988, 390, 1097, 579],
        [863, 401, 1073, 667]
      ],
      "22": [
        [865, 384, 977, 593],
        null,
        null,
        [863, 401, 1074, 668]
      ],
      "23": [
        [865, 382, 978, 592],
        [874, 409, 1012, 620],
        [1007, 388, 1101, 584],
        [863, 399, 1078, 670]
      ],
      "24": [
        [864, 382, 977, 592],
        [873, 409, 1010, 621],
        [1013, 388, 1102, 583],
        [863, 400, 1078, 669]
      ],
      "25": [
        [865, 377, 976, 591],
        [864, 408, 1009, 628],
        [1009, 389, 1103, 581],
        [863, 399, 1078, 669]
      ],
      "26": [
        [866, 375, 974, 591],
        null,
        null,
        [864, 398, 1078, 670]
      ],
      "27": [
        [865, 377, 973, 591],
        null,
        [1021, 390, 1105, 580],
        [862, 400, 1078, 669]
      ],
      "28": [
        [865, 379, 972, 589],
        null,
        [1024, 390, 1106, 580],
        [863, 421, 1072, 668]
      ],
      "29": [
        [866, 376, 968, 589],
        null,
        null,
        [862, 399, 1075, 669]
      ],
      "30": [
        [866, 376, 968, 589],
        null,
        null,
        [863, 398, 1075, 669]
      ],
      "31": [
        [866, 372, 969, 588],
        null,
        null,
        [864, 399, 1076, 669]
      ],
      "32": [
        [866, 369, 968, 585],
        null,
        null,
        [864, 398, 1074, 668]
      ],
      "33": [
        [866, 370, 968, 586],
        null,
        null,
        [867, 397, 1075, 669]
      ],
      "34": [
        [867, 369, 967, 584],
        null,
        null,
        [869, 397, 1078, 670]
      ],
      "35": [
        [867, 369, 967, 580],
        null,
        null,
        [874, 395, 1075, 671]
      ],
      "36": [
        [867, 368, 967, 579],
        null,
        null,
        [879, 394, 1078, 674]
      ],
      "37": [
        [867, 368, 967, 578],
        null,
        null,
        [881, 393, 1078, 674]
      ],
      "38": [
        [867, 366, 967, 578],
        null,
        null,
        [880, 389, 1075, 674]
      ],
      "39": [
        [868, 366, 968, 578],
        null,
        null,
        [881, 382, 1075, 677]
      ]
    },
    "2": {
      "0": [
        [1033.31, 387.11, 1128.46, 614.51],
        [876.47, 416.82, 1024.89, 620.93],
        [898.41, 411.54, 997.27, 604.75],
        [713.09, 396.13, 825.39, 710.63]
      ],
      "1": [
        [1041, 386, 1129, 614],
        [875, 414, 1024, 621],
        [898, 411, 996, 604],
        [711, 391, 821, 711]
      ],
      "2": [
        [1049, 385, 1132, 612],
        [875, 401, 1021, 621],
        [901, 407, 998, 604],
        [710, 386, 817, 710]
      ],
      "3": [
        [1054, 383, 1134, 609],
        [875, 396, 1020, 621],
        [901, 405, 1003, 604],
        [708, 410, 815, 710]
      ],
      "4": [
        [1055, 383, 1136, 609],
        [875, 399, 1018, 621],
        [902, 404, 1001, 604],
        [705, 407, 814, 710]
      ],
      "5": [
        [1057, 383, 1138, 607],
        [874, 412, 1017, 620],
        [902, 398, 1002, 604],
        [704, 406, 810, 710]
      ],
      "6": [
        [1058, 383, 1141, 590],
        [875, 412, 1015, 619],
        [901, 399, 1002, 605],
        [703, 403, 810, 709]
      ],
      "7": [
        [1061, 387, 1142, 604],
        [874, 412, 1015, 620],
        [901, 397, 1002, 605],
        [700, 400, 809, 710]
      ],
      "8": [
        [1063, 388, 1144, 603],
        [873, 413, 1013, 620],
        [901, 399, 1004, 605],
        [697, 399, 811, 708]
      ],
      "9": [
        [1064, 388, 1146, 605],
        [873, 413, 1014, 620],
        [901, 398, 1004, 605],
        [696, 400, 812, 709]
      ],
      "10": [
        [1067, 390, 1148, 601],
        [873, 413, 1013, 619],
        [903, 398, 1007, 606],
        [693, 400, 806, 705]
      ],
      "11": [
        [1069, 385, 1150, 592],
        [874, 411, 1012, 620],
        [904, 401, 1005, 607],
        [685, 401, 806, 702]
      ],
      "12": [
        [1068, 403, 1155, 608],
        [874, 411, 1013, 621],
        [903, 402, 1010, 608],
        [683, 402, 807, 706]
      ],
      "13": [
        [1070, 413, 1154, 605],
        [875, 412, 1012, 621],
        [905, 403, 1008, 607],
        [681, 403, 807, 707]
      ],
      "14": [
        [1073, 389, 1155, 599],
        [875, 413, 1009, 622],
        [906, 407, 1010, 607],
        [673, 403, 805, 711]
      ],
      "15": [
        [1073, 406, 1160, 611],
        [875, 411, 1006, 621],
        [907, 411, 1007, 607],
        [673, 410, 805, 711]
      ],
      "16": [
        [1075, 407, 1167, 615],
        [876, 411, 1007, 621],
        [907, 412, 1011, 608],
        [673, 410, 804, 715]
      ],
      "17": [
        [1076, 414, 1169, 614],
        [877, 410, 1006, 619],
        [909, 415, 1011, 609],
        [672, 415, 803, 723]
      ],
      "18": [
        [1078, 388, 1177, 602],
        [878, 409, 1003, 619],
        [909, 416, 1014, 609],
        [670, 423, 801, 731]
      ],
      "19": [
        [1079, 387, 1176, 605],
        [878, 408, 1009, 621],
        [910, 417, 1015, 608],
        [664, 424, 800, 786]
      ],
      "20": [
        [1080, 403, 1180, 601],
        [878, 408, 1008, 621],
        [912, 416, 1018, 608],
        [662, 425, 800, 793]
      ],
      "21": [
        [1083, 389, 1185, 601],
        [877, 408, 1012, 621],
        [913, 417, 1018, 609],
        [661, 430, 799, 800]
      ],
      "22": [
        [1085, 387, 1184, 596],
        [876, 408, 1013, 621],
        [915, 418, 1020, 610],
        [659, 428, 798, 803]
      ],
      "23": [
        [1083, 397, 1186, 594],
        [876, 408, 1013, 621],
        null,
        [657, 429, 795, 805]
      ],
      "24": [
        [1088, 401, 1189, 605],
        null,
        null,
        [655, 430, 793, 805]
      ],
      "25": [
        [1097, 390, 1187, 603],
        [871, 409, 1009, 623],
        null,
        [654, 429, 792, 805]
      ],
      "26": [
        [1096, 397, 1187, 591],
        [871, 403, 1008, 624],
        null,
        [653, 430, 790, 805]
      ],
      "27": [
        [1101, 389, 1188, 595],
        [869, 405, 1006, 623],
        null,
        [653, 430, 792, 805]
      ],
      "28": [
        [1101, 387, 1188, 591],
        [868, 406, 1005, 624],
        null,
        [654, 428, 791, 804]
      ],
      "29": [
        [1105, 380, 1188, 590],
        [867, 401, 1003, 625],
        null,
        [654, 428, 792, 805]
      ],
      "30": [
        [1106, 377, 1187, 590],
        [866, 392, 1002, 622],
        null,
        [655, 426, 793, 805]
      ],
      "31": [
        [1107, 375, 1186, 592],
        [866, 403, 999, 620],
        null,
        [655, 426, 794, 804]
      ],
      "32": [
        [1108, 374, 1187, 591],
        [866, 392, 998, 619],
        null,
        [656, 420, 796, 804]
      ],
      "33": [
        [1107, 375, 1187, 590],
        [866, 390, 994, 619],
        null,
        [656, 416, 798, 804]
      ],
      "34": [
        [1105, 373, 1188, 588],
        [867, 385, 992, 620],
        null,
        [657, 415, 800, 802]
      ],
      "35": [
        [1103, 373, 1187, 588],
        [867, 394, 991, 619],
        null,
        [656, 415, 801, 804]
      ],
      "36": [
        [1106, 370, 1188, 586],
        [867, 386, 990, 618],
        null,
        [656, 414, 804, 802]
      ],
      "37": [
        [1104, 368, 1187, 585],
        [868, 375, 987, 617],
        null,
        [657, 414, 808, 803]
      ],
      "38": [
        [1103, 368, 1190, 582],
        [868, 376, 979, 619],
        null,
        [656, 415, 810, 804]
      ],
      "39": [
        [1101, 368, 1190, 581],
        [867, 376, 964, 618],
        null,
        [657, 415, 813, 802]
      ]
    }
  }
}
